odoo/addons/asynchronous_invoice_email/README.rst
odoo/addons/asynchronous_invoice_email/__init__.py
odoo/addons/asynchronous_invoice_email/__manifest__.py
odoo/addons/asynchronous_invoice_email/i18n/es.po
odoo/addons/asynchronous_invoice_email/static/description/icon.png
odoo/addons/asynchronous_invoice_email/wizards/__init__.py
odoo/addons/asynchronous_invoice_email/wizards/account_invoice_send.py
odoo13_addon_asynchronous_invoice_email-13.0.1.0.0.dist-info/METADATA
odoo13_addon_asynchronous_invoice_email-13.0.1.0.0.dist-info/WHEEL
odoo13_addon_asynchronous_invoice_email-13.0.1.0.0.dist-info/top_level.txt
odoo13_addon_asynchronous_invoice_email-13.0.1.0.0.dist-info/RECORD
